.gitignore
COPYRIGHT
README
color-world.py
ez_setup.py
setup.py
testutils.py
colorworld/__init__.py
colorworld/colorworld.py
colorworld/country-codes.csv
colorworld/country.py
colorworld/world-template.svg
colorworld.egg-info/PKG-INFO
colorworld.egg-info/SOURCES.txt
colorworld.egg-info/dependency_links.txt
colorworld.egg-info/entry_points.txt
colorworld.egg-info/requires.txt
colorworld.egg-info/top_level.txt
consistency/default.svg
consistency/divisions.svg
consistency/longnames.svg
consistency/most-options.svg
consistency/units.svg
testdata/longnames.csv
testdata/longnames.svg
testdata/test.csv
testdata/whitespace.csv
testdata/whitespace.svg
tests/__init__.py
tests/test_colorworld.py
tests/test_executable.py
webpage/index.tmpl
webpage/make.py
webpage/sample.png