Metadata-Version: 1.0
Name: colorworld
Version: 0.3
Summary: A module and python script to produce colored world maps from lists of data for countries.
Home-page: http://tat.wright.name/colorworld/
Author: Tom Wright
Author-email: tat.wright@googlemail.com
License: BSD
Keywords: chloropleth colorworld color world map svg
Platform: UNKNOWN
Classifier: Programming Language :: Python :: 2.5
Classifier: License :: OSI Approved :: BSD License
Classifier: Development Status :: 4 - Beta
Classifier: Intended Audience :: Developers
Classifier: Intended Audience :: End Users/Desktop
Classifier: Topic :: Utilities
